{"name": "Yemen", "width": 4, "height": 23, "edit_mask": [{"row": null, "col": 0, "editable": false}, {"row": null, "col": 1, "editable": false}, {"row": 0, "col": null, "editable": false}, {"row": null, "col": 3, "type": "color"}, {"row": null, "col": 2, "type": "number", "min": 0, "max": null}, {"row": 0, "col": null, "type": "text"}, {"row": 0, "col": 2, "editable": true}], "contents": ["Governorate", "Population", "Population (1994) (People)", "Colour", "Aden", "925000", "404257", "#d95f02", "Abyan", "568000", "342628", "#7570b3", "Al Bayda'", "760000", "454608", "#d95f02", "Ad Dali", "720000", "330062", "#e7298a", "Al Hudaydah", "3189000", "1558513", "#7570b3", "Al Jawf", "589000", "347639", "#e7298a", "Al Mahrah", "150000", "56425", "#e6ab02", "Al Mahwit", "695000", "371595", "#e7298a", "Amanat Al Asimah", "2948472", "1003627", "#7570b3", "'Amran", "1052000", "731873", "#d95f02", "Dhamar", "1913000", "981674", "#e6ab02", "Hadramawt", "1424036", "755631", "#d95f02", "Hajjah", "2129000", "1091788", "#66a61e", "Ibb", "2837000", "1665054", "#66a61e", "Lahij", "983000", "555742", "#1b9e77", "Ma'rib", "336859", "181740", "#7570b3", "Raymah", "566000", "291533", "#66a61e", "Sa'dah", "1078000", "481617", "#e6ab02", "Sana'a", "1435528", "746812", "#1b9e77", "Shabwah", "632000", "364932", "#1b9e77", "Socotra", "64964", "NA", "#e7298a", "Ta'izz", "3182000", "1870057", "#e6ab02"]}