{"scale_x": 55.03464453254079, "scale_y": 55.03464453254079, "labels": [{"text": "GA", "x": 60.204487, "y": 61.319386}, {"text": "AS", "x": 172.01086, "y": 33.420712}, {"text": "CL", "x": 235.24345, "y": 117.06429}, {"text": "EX", "x": 160.5453, "y": 256.42651}, {"text": "AN", "x": 255.31161, "y": 363.45673}, {"text": "ML", "x": 241.03235, "y": 438.901}, {"text": "CE", "x": 336.94785, "y": 446.59381}, {"text": "CM", "x": 334.46936, "y": 247.50734}, {"text": "MD", "x": 289.9758, "y": 189.4024}, {"text": "CB", "x": 272.47681, "y": 39.688202}, {"text": "PV", "x": 353.29248, "y": 48.930798}, {"text": "NA", "x": 404.70795, "y": 65.778976}, {"text": "LO", "x": 360.2049, "y": 89.338203}, {"text": "AR", "x": 461.56775, "y": 128.21326}, {"text": "CT", "x": 583.09161, "y": 110.37489}, {"text": "VC", "x": 447.85901, "y": 246.661}, {"text": "MU", "x": 422.5463, "y": 327.78}, {"text": "PM", "x": 663.21301, "y": 235.686}], "lines": []}